tinyfive/__init__.py
tinyfive/machine.py
tinyfive-1.0.0.dist-info/METADATA
tinyfive-1.0.0.dist-info/WHEEL
tinyfive-1.0.0.dist-info/licenses/LICENSE
tinyfive-1.0.0.dist-info/RECORD
