Metadata-Version: 2.1
Name: tinyfive
Version: 1.0.0
Summary: TinyFive is a lightweight RISC-V emulator and assembler written entirely in Python
Project-URL: Homepage, https://github.com/OpenMachine-ai/tinyfive
Project-URL: Bug Tracker, https://github.com/OpenMachine-ai/tinyfive/issues
Author-email: Open Machine <tinyfive@openmachine.ai>
License-File: LICENSE
Classifier: License :: OSI Approved :: MIT License
Classifier: Operating System :: OS Independent
Classifier: Programming Language :: Python :: 3
Requires-Python: >=3.6
Requires-Dist: numpy>1.20.0
